django_gumby-0.1.1.dist-info/DESCRIPTION.rst
django_gumby-0.1.1.dist-info/METADATA
django_gumby-0.1.1.dist-info/metadata.json
django_gumby-0.1.1.dist-info/RECORD
django_gumby-0.1.1.dist-info/top_level.txt
django_gumby-0.1.1.dist-info/WHEEL
gumby/__init__.py
gumby/basehealthcheck.py
gumby/health_check.py
gumby/healthchecks.py
gumby/models.py
gumby/tasks.py
gumby/urls.py
gumby/utils.py
gumby/views.py
