Metadata-Version: 2.0
Name: django-gumby
Version: 0.1.1
Summary: Django health checks
Home-page: https://github.com/Kyperion/django-gumby
Author: Luis Morales
Author-email: luis.morales@kyperion.com
License: BSD
Keywords: django-gumby
Platform: UNKNOWN
Classifier: Development Status :: 2 - Pre-Alpha
Classifier: Framework :: Django
Classifier: Intended Audience :: Developers
Classifier: License :: OSI Approved :: BSD License
Classifier: Natural Language :: English
Classifier: Programming Language :: Python :: 2.7
Classifier: Programming Language :: Python :: 3
Classifier: Programming Language :: Python :: 3.3
